dbbackup_admin/__init__.py
dbbackup_admin/admin.py
dbbackup_admin/apps.py
dbbackup_admin/models.py
dbbackup_admin/urls.py
dbbackup_admin/views.py
dbbackup_admin/migrations/0001_initial.py
dbbackup_admin/migrations/__init__.py
django_dbbackup_admin-1.5.0.dist-info/LICENSE
django_dbbackup_admin-1.5.0.dist-info/METADATA
django_dbbackup_admin-1.5.0.dist-info/WHEEL
django_dbbackup_admin-1.5.0.dist-info/top_level.txt
django_dbbackup_admin-1.5.0.dist-info/RECORD
